MANIFEST.in
README.txt
setup.py
docs/HISTORY.txt
docs/LICENSE.txt
src/silva/__init__.py
src/silva.core.interfaces.egg-info/PKG-INFO
src/silva.core.interfaces.egg-info/SOURCES.txt
src/silva.core.interfaces.egg-info/dependency_links.txt
src/silva.core.interfaces.egg-info/entry_points.txt
src/silva.core.interfaces.egg-info/namespace_packages.txt
src/silva.core.interfaces.egg-info/not-zip-safe
src/silva.core.interfaces.egg-info/requires.txt
src/silva.core.interfaces.egg-info/top_level.txt
src/silva/core/__init__.py
src/silva/core/interfaces/__init__.py
src/silva/core/interfaces/adapters.py
src/silva/core/interfaces/auth.py
src/silva/core/interfaces/content.py
src/silva/core/interfaces/errors.py
src/silva/core/interfaces/events.py
src/silva/core/interfaces/extension.py
src/silva/core/interfaces/registry.py
src/silva/core/interfaces/service.py
src/silva/core/interfaces/silvaxml.py