Metadata-Version: 1.1
Name: silva.core.interfaces
Version: 3.0.4
Summary: Define Zope interfaces used in Silva
Home-page: http://infrae.com/products/silva
Author: Infrae
Author-email: info@infrae.com
License: BSD
Keywords: silva cms interfaces zope
Platform: UNKNOWN
Classifier: Framework :: Zope2
Classifier: License :: OSI Approved :: BSD License
Classifier: Programming Language :: Python
Classifier: Topic :: Software Development :: Libraries :: Python Modules
